LICENSE
MANIFEST.in
README.md
setup.py
djangotcha/.DS_Store
djangotcha/__init__.py
djangotcha/urls.py
djangotcha/views.py
djangotcha.egg-info/PKG-INFO
djangotcha.egg-info/SOURCES.txt
djangotcha.egg-info/dependency_links.txt
djangotcha.egg-info/top_level.txt
djangotcha/static/djangotcha/chart.js
djangotcha/static/djangotcha/core.js
djangotcha/templates/.DS_Store
djangotcha/templates/djangotcha/chart_gotcha.html
djangotcha/templates/djangotcha/gotcha.html
djangotcha/templatetags/__init__.py
djangotcha/templatetags/gotcha_tags.py