Metadata-Version: 1.1
Name: djangotcha
Version: 0.0.1
Summary: API Benchmark Tool for Django
Home-page: https://github.com/Hipo/djangotcha
Author: umitdincel
Author-email: dincelumit@gmail.com
License: MIT
Platform: UNKNOWN
Classifier: Programming Language :: Python
Classifier: Programming Language :: Python :: 2.7
